README.md
setup.cfg
setup.py
taurus_datajob_api/__init__.py
taurus_datajob_api/api_client.py
taurus_datajob_api/configuration.py
taurus_datajob_api/exceptions.py
taurus_datajob_api/rest.py
taurus_datajob_api.egg-info/PKG-INFO
taurus_datajob_api.egg-info/SOURCES.txt
taurus_datajob_api.egg-info/dependency_links.txt
taurus_datajob_api.egg-info/requires.txt
taurus_datajob_api.egg-info/top_level.txt
taurus_datajob_api/api/__init__.py
taurus_datajob_api/api/data_jobs_api.py
taurus_datajob_api/api/data_jobs_deployment_api.py
taurus_datajob_api/api/data_jobs_execution_api.py
taurus_datajob_api/api/data_jobs_properties_api.py
taurus_datajob_api/api/data_jobs_service_api.py
taurus_datajob_api/api/data_jobs_sources_api.py
taurus_datajob_api/models/__init__.py
taurus_datajob_api/models/data_job.py
taurus_datajob_api/models/data_job_api_info.py
taurus_datajob_api/models/data_job_config.py
taurus_datajob_api/models/data_job_contacts.py
taurus_datajob_api/models/data_job_deployment.py
taurus_datajob_api/models/data_job_deployment_status.py
taurus_datajob_api/models/data_job_execution.py
taurus_datajob_api/models/data_job_execution_request.py
taurus_datajob_api/models/data_job_mode.py
taurus_datajob_api/models/data_job_page.py
taurus_datajob_api/models/data_job_query_response.py
taurus_datajob_api/models/data_job_query_response_with_error.py
taurus_datajob_api/models/data_job_resources.py
taurus_datajob_api/models/data_job_schedule.py
taurus_datajob_api/models/data_job_summary.py
taurus_datajob_api/models/data_job_version.py
taurus_datajob_api/models/enable.py
taurus_datajob_api/models/error.py
test/test_data_job.py
test/test_data_job_api_info.py
test/test_data_job_config.py
test/test_data_job_contacts.py
test/test_data_job_deployment.py
test/test_data_job_deployment_status.py
test/test_data_job_execution.py
test/test_data_job_execution_request.py
test/test_data_job_mode.py
test/test_data_job_page.py
test/test_data_job_query_response.py
test/test_data_job_query_response_with_error.py
test/test_data_job_resources.py
test/test_data_job_schedule.py
test/test_data_job_summary.py
test/test_data_job_version.py
test/test_data_jobs_api.py
test/test_data_jobs_deployment_api.py
