Metadata-Version: 1.0
Name: taurus-datajob-api
Version: 3.1.3
Summary: Taurus Data Jobs
Home-page: UNKNOWN
Author: OpenAPI Generator community
Author-email: team@openapitools.org
License: UNKNOWN
Keywords: OpenAPI,OpenAPI-Generator,Taurus Data Jobs
Platform: UNKNOWN
